tpspy/__init__.py
tpspy/base.py
tpspy/client.py
tpspy/audit/__init__.py
tpspy/audit/audit.py
tpspy/auth/__init__.py
tpspy/auth/authutil.py
tpspy/auth/djangoutil.py
tpspy/message/__init__.py
tpspy/message/message.py
tpspy/metrics/__init__.py
tpspy/metrics/metrics.py
tpspy/metrics/resource_flow.py
tpspy/permission/__init__.py
tpspy/permission/permission.py
tpspy-0.9.2.dist-info/METADATA
tpspy-0.9.2.dist-info/WHEEL
tpspy-0.9.2.dist-info/top_level.txt
tpspy-0.9.2.dist-info/RECORD
