Metadata-Version: 2.1
Name: tpspy
Version: 0.9.2
Summary: UNKNOWN
Author: kangtian
License: All right reserved
Platform: UNKNOWN
Classifier: Programming Language :: Python
Classifier: License :: OSI Approved :: MIT License
Classifier: Operating System :: OS Independent
Requires-Dist: requests
